.hgignore
.hgtags
CHANGES.txt
LICENSE.txt
README.txt
setup.py
js/__init__.py
js.tinymce.egg-info/PKG-INFO
js.tinymce.egg-info/SOURCES.txt
js.tinymce.egg-info/dependency_links.txt
js.tinymce.egg-info/entry_points.txt
js.tinymce.egg-info/namespace_packages.txt
js.tinymce.egg-info/not-zip-safe
js.tinymce.egg-info/requires.txt
js.tinymce.egg-info/top_level.txt
js/tinymce/__init__.py
js/tinymce/test_tinymce.txt
js/tinymce/resources/jquery.tinymce.min.js
js/tinymce/resources/license.txt
js/tinymce/resources/tinymce.dev.js
js/tinymce/resources/tinymce.js
js/tinymce/resources/tinymce.min.js
js/tinymce/resources/classes/AddOnManager.js
js/tinymce/resources/classes/Compat.js
js/tinymce/resources/classes/DragDropOverrides.js
js/tinymce/resources/classes/Editor.js
js/tinymce/resources/classes/EditorCommands.js
js/tinymce/resources/classes/EditorManager.js
js/tinymce/resources/classes/EditorObservable.js
js/tinymce/resources/classes/EditorUpload.js
js/tinymce/resources/classes/EnterKey.js
js/tinymce/resources/classes/Env.js
js/tinymce/resources/classes/ErrorReporter.js
js/tinymce/resources/classes/FocusManager.js
js/tinymce/resources/classes/ForceBlocks.js
js/tinymce/resources/classes/Formatter.js
js/tinymce/resources/classes/InsertContent.js
js/tinymce/resources/classes/InsertList.js
js/tinymce/resources/classes/LegacyInput.js
js/tinymce/resources/classes/Mode.js
js/tinymce/resources/classes/NodeChange.js
js/tinymce/resources/classes/NotificationManager.js
js/tinymce/resources/classes/Register.js
js/tinymce/resources/classes/SelectionOverrides.js
js/tinymce/resources/classes/Shortcuts.js
js/tinymce/resources/classes/UndoManager.js
js/tinymce/resources/classes/WindowManager.js
js/tinymce/resources/classes/jquery.tinymce.js
js/tinymce/resources/classes/caret/CaretBookmark.js
js/tinymce/resources/classes/caret/CaretCandidate.js
js/tinymce/resources/classes/caret/CaretContainer.js
js/tinymce/resources/classes/caret/CaretPosition.js
js/tinymce/resources/classes/caret/CaretUtils.js
js/tinymce/resources/classes/caret/CaretWalker.js
js/tinymce/resources/classes/caret/FakeCaret.js
js/tinymce/resources/classes/caret/LineUtils.js
js/tinymce/resources/classes/caret/LineWalker.js
js/tinymce/resources/classes/content/LinkTargets.js
